[
  {
    "inputs": [
      {
        "internalType": "uint256",
        "name": "underlyingAmount_",
        "type": "uint256"
      },
      {
        "internalType": "uint256",
        "name": "takeFees_",
        "type": "uint256"
      }
    ],
    "name": "_depositProvider",
    "outputs": [],
    "stateMutability": "nonpayable",
    "type": "function"
  },
  {
    "inputs": [
      {
        "internalType": "address",
        "name": "to_",
        "type": "address"
      },
      {
        "internalType": "uint256",
        "name": "amount_",
        "type": "uint256"
      }
    ],
    "name": "_sendUnderlying",
    "outputs": [],
    "stateMutability": "nonpayable",
    "type": "function"
  },
  {
    "inputs": [
      {
        "internalType": "address",
        "name": "from_",
        "type": "address"
      },
      {
        "internalType": "uint256",
        "name": "amount_",
        "type": "uint256"
      }
    ],
    "name": "_takeUnderlying",
    "outputs": [],
    "stateMutability": "nonpayable",
    "type": "function"
  },
  {
    "inputs": [
      {
        "internalType": "uint256",
        "name": "underlyingAmount_",
        "type": "uint256"
      },
      {
        "internalType": "uint256",
        "name": "takeFees_",
        "type": "uint256"
      }
    ],
    "name": "_withdrawProvider",
    "outputs": [],
    "stateMutability": "nonpayable",
    "type": "function"
  },
  {
    "inputs": [],
    "name": "controller",
    "outputs": [
      {
        "internalType": "address",
        "name": "",
        "type": "address"
      }
    ],
    "stateMutability": "view",
    "type": "function"
  },
  {
    "inputs": [
      {
        "internalType": "address",
        "name": "newController_",
        "type": "address"
      }
    ],
    "name": "setController",
    "outputs": [],
    "stateMutability": "nonpayable",
    "type": "function"
  },
  {
    "inputs": [],
    "name": "smartYield",
    "outputs": [
      {
        "internalType": "address",
        "name": "",
        "type": "address"
      }
    ],
    "stateMutability": "view",
    "type": "function"
  },
  {
    "inputs": [],
    "name": "transferFees",
    "outputs": [],
    "stateMutability": "nonpayable",
    "type": "function"
  },
  {
    "inputs": [],
    "name": "underlyingBalance",
    "outputs": [
      {
        "internalType": "uint256",
        "name": "",
        "type": "uint256"
      }
    ],
    "stateMutability": "nonpayable",
    "type": "function"
  },
  {
    "inputs": [],
    "name": "underlyingFees",
    "outputs": [
      {
        "internalType": "uint256",
        "name": "",
        "type": "uint256"
      }
    ],
    "stateMutability": "view",
    "type": "function"
  }
]
